ptqs/__init__.py
ptqs/coolptqs.py
coolptqs-1.0.0.dist-info/METADATA
coolptqs-1.0.0.dist-info/WHEEL
coolptqs-1.0.0.dist-info/top_level.txt
coolptqs-1.0.0.dist-info/RECORD
