Metadata-Version: 2.1
Name: coolptqs
Version: 1.0.0
Requires-Dist: colored
Requires-Dist: datetime
